mpd_box/__init__.py
mpd_box/daemon.py
mpd_box/manage.py
mpd_box/tests.py
mpd_box/core/__init__.py
mpd_box/core/config.py
mpd_box/core/logger.py
mpd_box/core/management.py
mpd_box/core/utils.py
mpd_box/readers/__init__.py
mpd_box/server/__init__.py
mpd_box/server/views.py
mpd_box-0.1.1.data/scripts/mpd-box
mpd_box-0.1.1.data/scripts/mpd-box-daemon
mpd_box-0.1.1.dist-info/DESCRIPTION.rst
mpd_box-0.1.1.dist-info/METADATA
mpd_box-0.1.1.dist-info/RECORD
mpd_box-0.1.1.dist-info/WHEEL
mpd_box-0.1.1.dist-info/metadata.json
mpd_box-0.1.1.dist-info/top_level.txt
